pydeequ3/__init__.py
pydeequ3/analyzers.py
pydeequ3/anomaly_detection.py
pydeequ3/checks.py
pydeequ3/configs.py
pydeequ3/metrics.py
pydeequ3/pandas_utils.py
pydeequ3/profiles.py
pydeequ3/repository.py
pydeequ3/scala_utils.py
pydeequ3/suggestions.py
pydeequ3/verification.py
pydeequ3-0.1.8.dist-info/WHEEL
pydeequ3-0.1.8.dist-info/METADATA
pydeequ3-0.1.8.dist-info/RECORD
